test/__init__.py
test/base.py
test/test_add_multi.py
test/test_add_single.py
test/test_bin.py
test/test_builder.py
test/test_custom.py
test/test_gen_multi.py
test/test_gen_single.py
test/test_misuse.py
test/test_seed_schema.py
tfgenson/__init__.py
tfgenson/schema/__init__.py
tfgenson/schema/builder.py
tfgenson/schema/node.py
tfgenson/schema/strategies/__init__.py
tfgenson/schema/strategies/array.py
tfgenson/schema/strategies/base.py
tfgenson/schema/strategies/object.py
tfgenson/schema/strategies/scalar.py
tfgenson-1.2.1a1.dist-info/AUTHORS.rst
tfgenson-1.2.1a1.dist-info/LICENSE
tfgenson-1.2.1a1.dist-info/METADATA
tfgenson-1.2.1a1.dist-info/WHEEL
tfgenson-1.2.1a1.dist-info/top_level.txt
tfgenson-1.2.1a1.dist-info/zip-safe
tfgenson-1.2.1a1.dist-info/RECORD
