Metadata-Version: 2.1
Name: tfgenson
Version: 1.2.1a1
Summary: TFGenSON is a powerful, user-friendly JSON Schema generator.
Home-page: https://github.com/davedotdev/tfgenson/
Author: Jon Wolverton, David Gee
Author-email: me@dave.dev
License: MIT
Download-URL: https://github.com/davedotdev/TFGenSON/tarball/v1.2.1a1
Keywords: json,schema,json-schema,jsonschema,object,generate,generator,builder,merge,draft 7,validate,validation
Platform: UNKNOWN
Classifier: Development Status :: 5 - Production/Stable
Classifier: Intended Audience :: Developers
Classifier: Natural Language :: English
Classifier: License :: OSI Approved :: MIT License
Classifier: Operating System :: OS Independent
Classifier: Programming Language :: Python
Classifier: Programming Language :: Python :: 3
Classifier: Programming Language :: Python :: 3.4
Classifier: Programming Language :: Python :: 3.5
Classifier: Programming Language :: Python :: 3.6
Classifier: Programming Language :: Python :: 3.7
Classifier: Programming Language :: Python :: 3.8
Classifier: Topic :: Software Development :: Code Generators
Classifier: Topic :: Software Development :: Libraries :: Python Modules
Classifier: Topic :: Utilities
Requires-Python: >=3.6
